{
	"ident": 1106,
	"order": 90,
	"objtype": "kComponent",
	"componentlib": "jsLabel",
	"componentctrl": "Label Object",
	"properties": {
		"align": "kLeftJst",
		"alpha": 255,
		"backalpha": 255,
		"backcolor": "RGB(255,255,255)",
		"contextmenu": "",
		"cssclassname": "",
		"dataname": "",
		"desgroup": 0,
		"designactive": true,
		"deslock": false,
		"disabledefaultcontextmenu": false,
		"disablesystemfocus": true,
		"dropmode": "kAcceptNone",
		"enabled": false,
		"events": "",
		"fieldstyle": "",
		"font": 1,
		"fontsize": 8,
		"fontstyle": "kPlain",
		"objlink": 65625,
		"preventlayoutanimation": false,
		"text": "Regular",
		"textcolor": "kColorDefault",
		"textishtml": false,
		"tooltip": "",
		"userinfo": "",
		"vertcentertext": false,
		"visible": true
	},
	"screensizes": [
		{
			"name": "kSSZDesktop",
			"left": 3,
			"top": 3,
			"width": 120,
			"height": 16,
			"edgefloat": "kEFnone",
			"dragborder": false,
			"errortextpos": "kJSErrorTextPosUnder"
		}
	]
}
