{
	"ident": 1026,
	"order": 16389,
	"objtype": "kText",
	"properties": {
		"align": "kLeftJst",
		"backcolor": "kColorBackFill",
		"backpattern": 15,
		"designactive": true,
		"edgefloat": "kEFnone",
		"fieldstyle": "",
		"font": 1,
		"fontsize": 15,
		"fontstyle": "kPlain",
		"forecolor": "kColorForeFill",
		"height": 122,
		"left": 26,
		"objlink": 0,
		"text": {
			"type": 14,
			"calc": "\u001B\u000200000001#Example 2: Print to temp file...\u001B\u000200000000#\r\rThe remote form \u001B\u000200000002#e1_RemoteForm\u001B\u000200000000# and the remote task \u001B\u000200000002#e1_RemoteTask\u001B\u000200000000# demonstrate how to print reports to a binary variable and return that PDF data to the client for displaying in an embed control or a seperate browser window."
		},
		"textcolor": "kColorWindowText",
		"top": 357,
		"userinfo": "",
		"vertcentertext": false,
		"visible": true,
		"width": 693
	}
}
